dotctl/__init__.py
dotctl/arg_manager.py
dotctl/exception.py
dotctl/main.py
dotctl/paths.py
dotctl/utils.py
dotctl/validators.py
dotctl/actions/__init__.py
dotctl/actions/activator.py
dotctl/actions/creator.py
dotctl/actions/exporter.py
dotctl/actions/importer.py
dotctl/actions/initializer.py
dotctl/actions/lister.py
dotctl/actions/puller.py
dotctl/actions/remover.py
dotctl/actions/saver.py
dotctl/actions/switcher.py
dotctl/actions/wiper.py
dotctl/handlers/__init__.py
dotctl/handlers/config_handler.py
dotctl/handlers/data_handler.py
dotctl/handlers/git_handler.py
dotctl/handlers/hooks_handler.py
dotctl/hooks/post_apply.sh
dotctl/hooks/pre_apply.sh
dotctl/templates/__init__.py
dotctl/templates/dev.yaml
dotctl/templates/kde.yaml
dotctl/templates/other.yaml
dotctl-1.0.9.dist-info/licenses/LICENSE
dotctl-1.0.9.dist-info/METADATA
dotctl-1.0.9.dist-info/WHEEL
dotctl-1.0.9.dist-info/entry_points.txt
dotctl-1.0.9.dist-info/top_level.txt
dotctl-1.0.9.dist-info/RECORD
