Metadata-Version: 2.4
Name: dotctl
Version: 1.0.9
Summary: A powerful CLI tool to profile your OS by saving, applying, exporting, and importing system configurations as named profiles. Designed to manage dot files and service configurations in a centralized Git repository (local or remote), dotctl enables seamless system replication across machines. Supports pre/post hook scripts, making it ideal for setting up servers or desktops with consistent environments.
Author-email: Pankaj Jackson <pankajackson@live.co.uk>
License-Expression: MIT
Project-URL: Homepage, https://github.com/pankajackson/dotctl
Project-URL: Bug Tracker, https://github.com/pankajackson/dotctl/issues
Project-URL: Source, https://github.com/pankajackson/dotctl
Keywords: dotfiles,config,settings,backup,dotfile-manager
Classifier: Programming Language :: Python :: 3.10
Classifier: Programming Language :: Python :: 3.11
Classifier: Programming Language :: Python :: 3.12
Classifier: Programming Language :: Python :: 3.13
Classifier: Development Status :: 4 - Beta
Classifier: Intended Audience :: End Users/Desktop
Classifier: Operating System :: POSIX :: Linux
Classifier: Topic :: System :: Archiving :: Backup
Classifier: Topic :: Utilities
Requires-Python: >=3.10
License-File: LICENSE
Requires-Dist: PyYAML
Requires-Dist: gitpython
Dynamic: license-file
